certbot_acme_dns/__init__.py
certbot_acme_dns/plugin.py
certbot_acme_dns/py.typed
certbot_acme_dns/_internal/__init__.py
certbot_acme_dns/_internal/acme_dns.py
certbot_acme_dns/_internal/caa.py
certbot_acme_dns/_internal/util.py
certbot_acme_dns-0.3.1.dist-info/LICENSE
certbot_acme_dns-0.3.1.dist-info/METADATA
certbot_acme_dns-0.3.1.dist-info/WHEEL
certbot_acme_dns-0.3.1.dist-info/entry_points.txt
certbot_acme_dns-0.3.1.dist-info/top_level.txt
certbot_acme_dns-0.3.1.dist-info/RECORD
