Metadata-Version: 2.1
Name: certbot-acme-dns
Version: 0.3.1
Summary: ACME DNS Authenticator plugin for Certbot
Author-email: Patrik Hagara <patrihagar+certbot-acme-dns@gmail.com>
License: BSD-2-Clause
Project-URL: repository, https://github.com/phagara/certbot-acme-dns
Classifier: Development Status :: 3 - Alpha
Classifier: Environment :: Plugins
Classifier: Intended Audience :: System Administrators
Classifier: License :: OSI Approved :: BSD License
Classifier: Operating System :: OS Independent
Classifier: Programming Language :: Python :: 3 :: Only
Classifier: Programming Language :: Python :: 3.8
Classifier: Topic :: Internet :: WWW/HTTP :: HTTP Servers
Classifier: Topic :: Security
Classifier: Topic :: System :: Networking
Requires-Python: >=3.8
License-File: LICENSE
Requires-Dist: acme
Requires-Dist: certbot
Requires-Dist: dnspython
Requires-Dist: requests
Requires-Dist: setuptools
Requires-Dist: zope.component
Requires-Dist: zope.interface
